llama_index/readers/bitbucket/__init__.py
llama_index/readers/bitbucket/base.py
llama_index_readers_bitbucket-0.4.1.dist-info/METADATA
llama_index_readers_bitbucket-0.4.1.dist-info/WHEEL
llama_index_readers_bitbucket-0.4.1.dist-info/licenses/LICENSE
llama_index_readers_bitbucket-0.4.1.dist-info/RECORD
