Metadata-Version: 2.4
Name: llama-index-readers-bitbucket
Version: 0.4.1
Summary: llama-index readers bitbucket integration
Author-email: Your Name <you@example.com>
Maintainer: lejdiprifti
License-Expression: MIT
License-File: LICENSE
Keywords: bitbucket,project,repository
Requires-Python: <4.0,>=3.9
Requires-Dist: llama-index-core<0.15,>=0.13.0
